podcasts/__init__.py
podcasts/api.py
podcasts/constants.py
podcasts/episode_worker.py
podcasts/episodes_driver.py
podcasts/itunes.py
podcasts/log.py
podcasts/series_crawler.py
podcasts/series_driver.py
podcasts/series_worker.py
podcasts/site_crawler.py
podcasts/top_series_for_topic.py
podcasts/models/__init__.py
podcasts/models/entity.py
podcasts/models/episode.py
podcasts/models/series.py
podcasts/storers/__init__.py
podcasts/storers/json_storer.py
podcasts/storers/storer.py
podcasts/tests/__init__.py
podfetch-1.0.8.dist-info/DESCRIPTION.rst
podfetch-1.0.8.dist-info/METADATA
podfetch-1.0.8.dist-info/RECORD
podfetch-1.0.8.dist-info/WHEEL
podfetch-1.0.8.dist-info/metadata.json
podfetch-1.0.8.dist-info/top_level.txt
