Metadata-Version: 2.0
Name: podfetch
Version: 1.0.8
Summary: Podcast Series / Episodes Data Retrieval and Storage in Python
Home-page: https://github.com/cuappdev/podfetch
Author: Cornell AppDev
Author-email: cornellappdev@gmail.com
License: MIT
Platform: UNKNOWN
Classifier: Development Status :: 4 - Beta
Classifier: Intended Audience :: Developers
Classifier: License :: OSI Approved :: MIT License
Classifier: Operating System :: OS Independent
Classifier: Programming Language :: Python
Classifier: Topic :: Internet
Classifier: Topic :: Multimedia
Classifier: Topic :: Software Development :: Libraries :: Python Modules
Requires-Dist: appdirs (>=1.4.2)
Requires-Dist: feedparser (>=5.2.1)
Requires-Dist: lxml (>=3.7.3)
Requires-Dist: packaging (>=16.8)
Requires-Dist: pyparsing (>=2.1.10)
Requires-Dist: requests (>=2.13.0)
Requires-Dist: six (>=1.10.0)
